log_parser/__init__.py
log_parser/__main__.py
log_parser/__version__.py
log_parser/cli/__init__.py
log_parser/cli/__main__.py
log_parser/cli/cli.py
log_parser/cli/patterns.py
log_parser/log_parser.py
log_parser/showcase/__init__.py
log_parser/showcase/__main__.py
log_parser/showcase/access.log
log_parser/showcase/showcase.py
task4-1.0.2.dist-info/entry_points.txt
task4-1.0.2.dist-info/LICENSE
task4-1.0.2.dist-info/METADATA
task4-1.0.2.dist-info/WHEEL
task4-1.0.2.dist-info/RECORD
