Metadata-Version: 2.1
Name: task4
Version: 1.0.2
Summary: Log file parser CLI and library
License: MIT
Author: Bill.Avramenko
Author-email: billavramenko@gmail.com
Requires-Python: >=3.8,<4.0
Classifier: License :: OSI Approved :: MIT License
Classifier: Programming Language :: Python :: 3
Classifier: Programming Language :: Python :: 3.8
Classifier: Programming Language :: Python :: 3.9
Classifier: Programming Language :: Python :: 3.10
Classifier: Programming Language :: Python :: 3.11
Requires-Dist: questionary (>=1.10.0,<2.0.0)
